{
  "documents": [
    {
      "document_id": "salary_slip_genuine_001",
      "document_type": "salary_slip",
      "label": "genuine",
      "ocr_confidence": 0.95,
      "employee_name": "Employee 1",
      "employee_id": "EMP0001",
      "pan_number": "ABCDE0001F",
      "uan_number": "100200300001",
      "gross_salary": 72500,
      "net_salary": 66800,
      "fraud_score": 5.0
    },
    {
      "document_id": "salary_slip_genuine_002",
      "document_type": "salary_slip",
      "label": "genuine",
      "ocr_confidence": 0.95,
      "employee_name": "Employee 2",
      "employee_id": "EMP0002",
      "pan_number": "ABCDE0002F",
      "uan_number": "100200300002",
      "gross_salary": 72500,
      "net_salary": 66800,
      "fraud_score": 5.0
    },
    {
      "document_id": "salary_slip_genuine_003",
      "document_type": "salary_slip",
      "label": "genuine",
      "ocr_confidence": 0.95,
      "employee_name": "Employee 3",
      "employee_id": "EMP0003",
      "pan_number": "ABCDE0003F",
      "uan_number": "100200300003",
      "gross_salary": 72500,
      "net_salary": 66800,
      "fraud_score": 5.0
    },
    {
      "document_id": "salary_slip_genuine_004",
      "document_type": "salary_slip",
      "label": "genuine",
      "ocr_confidence": 0.95,
      "employee_name": "Employee 4",
      "employee_id": "EMP0004",
      "pan_number": "ABCDE0004F",
      "uan_number": "100200300004",
      "gross_salary": 72500,
      "net_salary": 66800,
      "fraud_score": 5.0
    },
    {
      "document_id": "salary_slip_genuine_005",
      "document_type": "salary_slip",
      "label": "genuine",
      "ocr_confidence": 0.95,
      "employee_name": "Employee 5",
      "employee_id": "EMP0005",
      "pan_number": "ABCDE0005F",
      "uan_number": "100200300005",
      "gross_salary": 72500,
      "net_salary": 66800,
      "fraud_score": 5.0
    },
    {
      "document_id": "salary_slip_genuine_006",
      "document_type": "salary_slip",
      "label": "genuine",
      "ocr_confidence": 0.95,
      "employee_name": "Employee 6",
      "employee_id": "EMP0006",
      "pan_number": "ABCDE0006F",
      "uan_number": "100200300006",
      "gross_salary": 72500,
      "net_salary": 66800,
      "fraud_score": 5.0
    },
    {
      "document_id": "salary_slip_genuine_007",
      "document_type": "salary_slip",
      "label": "genuine",
      "ocr_confidence": 0.95,
      "employee_name": "Employee 7",
      "employee_id": "EMP0007",
      "pan_number": "ABCDE0007F",
      "uan_number": "100200300007",
      "gross_salary": 72500,
      "net_salary": 66800,
      "fraud_score": 5.0
    },
    {
      "document_id": "salary_slip_genuine_008",
      "document_type": "salary_slip",
      "label": "genuine",
      "ocr_confidence": 0.95,
      "employee_name": "Employee 8",
      "employee_id": "EMP0008",
      "pan_number": "ABCDE0008F",
      "uan_number": "100200300008",
      "gross_salary": 72500,
      "net_salary": 66800,
      "fraud_score": 5.0
    },
    {
      "document_id": "salary_slip_genuine_009",
      "document_type": "salary_slip",
      "label": "genuine",
      "ocr_confidence": 0.95,
      "employee_name": "Employee 9",
      "employee_id": "EMP0009",
      "pan_number": "ABCDE0009F",
      "uan_number": "100200300009",
      "gross_salary": 72500,
      "net_salary": 66800,
      "fraud_score": 5.0
    },
    {
      "document_id": "salary_slip_genuine_010",
      "document_type": "salary_slip",
      "label": "genuine",
      "ocr_confidence": 0.95,
      "employee_name": "Employee 10",
      "employee_id": "EMP0010",
      "pan_number": "ABCDE0010F",
      "uan_number": "100200300010",
      "gross_salary": 72500,
      "net_salary": 66800,
      "fraud_score": 5.0
    },
    {
      "document_id": "salary_slip_genuine_011",
      "document_type": "salary_slip",
      "label": "genuine",
      "ocr_confidence": 0.95,
      "employee_name": "Employee 11",
      "employee_id": "EMP0011",
      "pan_number": "ABCDE0011F",
      "uan_number": "100200300011",
      "gross_salary": 72500,
      "net_salary": 66800,
      "fraud_score": 5.0
    },
    {
      "document_id": "salary_slip_genuine_012",
      "document_type": "salary_slip",
      "label": "genuine",
      "ocr_confidence": 0.95,
      "employee_name": "Employee 12",
      "employee_id": "EMP0012",
      "pan_number": "ABCDE0012F",
      "uan_number": "100200300012",
      "gross_salary": 72500,
      "net_salary": 66800,
      "fraud_score": 5.0
    },
    {
      "document_id": "salary_slip_genuine_013",
      "document_type": "salary_slip",
      "label": "genuine",
      "ocr_confidence": 0.95,
      "employee_name": "Employee 13",
      "employee_id": "EMP0013",
      "pan_number": "ABCDE0013F",
      "uan_number": "100200300013",
      "gross_salary": 72500,
      "net_salary": 66800,
      "fraud_score": 5.0
    },
    {
      "document_id": "salary_slip_genuine_014",
      "document_type": "salary_slip",
      "label": "genuine",
      "ocr_confidence": 0.95,
      "employee_name": "Employee 14",
      "employee_id": "EMP0014",
      "pan_number": "ABCDE0014F",
      "uan_number": "100200300014",
      "gross_salary": 72500,
      "net_salary": 66800,
      "fraud_score": 5.0
    },
    {
      "document_id": "salary_slip_genuine_015",
      "document_type": "salary_slip",
      "label": "genuine",
      "ocr_confidence": 0.95,
      "employee_name": "Employee 15",
      "employee_id": "EMP0015",
      "pan_number": "ABCDE0015F",
      "uan_number": "100200300015",
      "gross_salary": 72500,
      "net_salary": 66800,
      "fraud_score": 5.0
    },
    {
      "document_id": "salary_slip_tampered_001",
      "document_type": "salary_slip",
      "label": "tampered",
      "ocr_confidence": 0.95,
      "employee_name": "Employee 1",
      "employee_id": "EMP0001",
      "pan_number": "ABCDE0001F",
      "uan_number": "100200300001",
      "gross_salary": 72500,
      "net_salary": 96800,
      "fraud_score": 95.0
    },
    {
      "document_id": "salary_slip_tampered_002",
      "document_type": "salary_slip",
      "label": "tampered",
      "ocr_confidence": 0.95,
      "employee_name": "Employee 2",
      "employee_id": "EMP0002",
      "pan_number": "ABCDE0002F",
      "uan_number": "100200300002",
      "gross_salary": 72500,
      "net_salary": 96800,
      "fraud_score": 95.0
    },
    {
      "document_id": "salary_slip_tampered_003",
      "document_type": "salary_slip",
      "label": "tampered",
      "ocr_confidence": 0.95,
      "employee_name": "Employee 3",
      "employee_id": "EMP0003",
      "pan_number": "ABCDE0003F",
      "uan_number": "100200300003",
      "gross_salary": 72500,
      "net_salary": 96800,
      "fraud_score": 95.0
    },
    {
      "document_id": "salary_slip_tampered_004",
      "document_type": "salary_slip",
      "label": "tampered",
      "ocr_confidence": 0.95,
      "employee_name": "Employee 4",
      "employee_id": "EMP0004",
      "pan_number": "ABCDE0004F",
      "uan_number": "100200300004",
      "gross_salary": 72500,
      "net_salary": 96800,
      "fraud_score": 95.0
    },
    {
      "document_id": "salary_slip_tampered_005",
      "document_type": "salary_slip",
      "label": "tampered",
      "ocr_confidence": 0.95,
      "employee_name": "Employee 5",
      "employee_id": "EMP0005",
      "pan_number": "ABCDE0005F",
      "uan_number": "100200300005",
      "gross_salary": 72500,
      "net_salary": 96800,
      "fraud_score": 95.0
    },
    {
      "document_id": "salary_slip_tampered_006",
      "document_type": "salary_slip",
      "label": "tampered",
      "ocr_confidence": 0.95,
      "employee_name": "Employee 6",
      "employee_id": "EMP0006",
      "pan_number": "ABCDE0006F",
      "uan_number": "100200300006",
      "gross_salary": 72500,
      "net_salary": 96800,
      "fraud_score": 95.0
    },
    {
      "document_id": "salary_slip_tampered_007",
      "document_type": "salary_slip",
      "label": "tampered",
      "ocr_confidence": 0.95,
      "employee_name": "Employee 7",
      "employee_id": "EMP0007",
      "pan_number": "ABCDE0007F",
      "uan_number": "100200300007",
      "gross_salary": 72500,
      "net_salary": 96800,
      "fraud_score": 95.0
    },
    {
      "document_id": "salary_slip_tampered_008",
      "document_type": "salary_slip",
      "label": "tampered",
      "ocr_confidence": 0.95,
      "employee_name": "Employee 8",
      "employee_id": "EMP0008",
      "pan_number": "ABCDE0008F",
      "uan_number": "100200300008",
      "gross_salary": 72500,
      "net_salary": 96800,
      "fraud_score": 95.0
    },
    {
      "document_id": "salary_slip_tampered_009",
      "document_type": "salary_slip",
      "label": "tampered",
      "ocr_confidence": 0.95,
      "employee_name": "Employee 9",
      "employee_id": "EMP0009",
      "pan_number": "ABCDE0009F",
      "uan_number": "100200300009",
      "gross_salary": 72500,
      "net_salary": 96800,
      "fraud_score": 95.0
    },
    {
      "document_id": "salary_slip_tampered_010",
      "document_type": "salary_slip",
      "label": "tampered",
      "ocr_confidence": 0.95,
      "employee_name": "Employee 10",
      "employee_id": "EMP0010",
      "pan_number": "ABCDE0010F",
      "uan_number": "100200300010",
      "gross_salary": 72500,
      "net_salary": 96800,
      "fraud_score": 95.0
    },
    {
      "document_id": "salary_slip_tampered_011",
      "document_type": "salary_slip",
      "label": "tampered",
      "ocr_confidence": 0.95,
      "employee_name": "Employee 11",
      "employee_id": "EMP0011",
      "pan_number": "ABCDE0011F",
      "uan_number": "100200300011",
      "gross_salary": 72500,
      "net_salary": 96800,
      "fraud_score": 95.0
    },
    {
      "document_id": "salary_slip_tampered_012",
      "document_type": "salary_slip",
      "label": "tampered",
      "ocr_confidence": 0.95,
      "employee_name": "Employee 12",
      "employee_id": "EMP0012",
      "pan_number": "ABCDE0012F",
      "uan_number": "100200300012",
      "gross_salary": 72500,
      "net_salary": 96800,
      "fraud_score": 95.0
    },
    {
      "document_id": "salary_slip_tampered_013",
      "document_type": "salary_slip",
      "label": "tampered",
      "ocr_confidence": 0.95,
      "employee_name": "Employee 13",
      "employee_id": "EMP0013",
      "pan_number": "ABCDE0013F",
      "uan_number": "100200300013",
      "gross_salary": 72500,
      "net_salary": 96800,
      "fraud_score": 95.0
    },
    {
      "document_id": "salary_slip_tampered_014",
      "document_type": "salary_slip",
      "label": "tampered",
      "ocr_confidence": 0.95,
      "employee_name": "Employee 14",
      "employee_id": "EMP0014",
      "pan_number": "ABCDE0014F",
      "uan_number": "100200300014",
      "gross_salary": 72500,
      "net_salary": 96800,
      "fraud_score": 95.0
    },
    {
      "document_id": "salary_slip_tampered_015",
      "document_type": "salary_slip",
      "label": "tampered",
      "ocr_confidence": 0.95,
      "employee_name": "Employee 15",
      "employee_id": "EMP0015",
      "pan_number": "ABCDE0015F",
      "uan_number": "100200300015",
      "gross_salary": 72500,
      "net_salary": 96800,
      "fraud_score": 95.0
    },
    {
      "document_id": "bank_statement_genuine_001",
      "document_type": "bank_statement",
      "label": "genuine",
      "ocr_confidence": 0.95,
      "account_holder": "Customer 1",
      "account_number": "XXXX4589",
      "ifsc_code": "HDFC0001234",
      "opening_balance": 85420,
      "closing_balance": 144291,
      "fraud_score": 8.0
    },
    {
      "document_id": "bank_statement_genuine_002",
      "document_type": "bank_statement",
      "label": "genuine",
      "ocr_confidence": 0.95,
      "account_holder": "Customer 2",
      "account_number": "XXXX4589",
      "ifsc_code": "HDFC0001234",
      "opening_balance": 85420,
      "closing_balance": 144291,
      "fraud_score": 8.0
    },
    {
      "document_id": "bank_statement_genuine_003",
      "document_type": "bank_statement",
      "label": "genuine",
      "ocr_confidence": 0.95,
      "account_holder": "Customer 3",
      "account_number": "XXXX4589",
      "ifsc_code": "HDFC0001234",
      "opening_balance": 85420,
      "closing_balance": 144291,
      "fraud_score": 8.0
    },
    {
      "document_id": "bank_statement_genuine_004",
      "document_type": "bank_statement",
      "label": "genuine",
      "ocr_confidence": 0.95,
      "account_holder": "Customer 4",
      "account_number": "XXXX4589",
      "ifsc_code": "HDFC0001234",
      "opening_balance": 85420,
      "closing_balance": 144291,
      "fraud_score": 8.0
    },
    {
      "document_id": "bank_statement_genuine_005",
      "document_type": "bank_statement",
      "label": "genuine",
      "ocr_confidence": 0.95,
      "account_holder": "Customer 5",
      "account_number": "XXXX4589",
      "ifsc_code": "HDFC0001234",
      "opening_balance": 85420,
      "closing_balance": 144291,
      "fraud_score": 8.0
    },
    {
      "document_id": "bank_statement_genuine_006",
      "document_type": "bank_statement",
      "label": "genuine",
      "ocr_confidence": 0.95,
      "account_holder": "Customer 6",
      "account_number": "XXXX4589",
      "ifsc_code": "HDFC0001234",
      "opening_balance": 85420,
      "closing_balance": 144291,
      "fraud_score": 8.0
    },
    {
      "document_id": "bank_statement_genuine_007",
      "document_type": "bank_statement",
      "label": "genuine",
      "ocr_confidence": 0.95,
      "account_holder": "Customer 7",
      "account_number": "XXXX4589",
      "ifsc_code": "HDFC0001234",
      "opening_balance": 85420,
      "closing_balance": 144291,
      "fraud_score": 8.0
    },
    {
      "document_id": "bank_statement_genuine_008",
      "document_type": "bank_statement",
      "label": "genuine",
      "ocr_confidence": 0.95,
      "account_holder": "Customer 8",
      "account_number": "XXXX4589",
      "ifsc_code": "HDFC0001234",
      "opening_balance": 85420,
      "closing_balance": 144291,
      "fraud_score": 8.0
    },
    {
      "document_id": "bank_statement_genuine_009",
      "document_type": "bank_statement",
      "label": "genuine",
      "ocr_confidence": 0.95,
      "account_holder": "Customer 9",
      "account_number": "XXXX4589",
      "ifsc_code": "HDFC0001234",
      "opening_balance": 85420,
      "closing_balance": 144291,
      "fraud_score": 8.0
    },
    {
      "document_id": "bank_statement_genuine_010",
      "document_type": "bank_statement",
      "label": "genuine",
      "ocr_confidence": 0.95,
      "account_holder": "Customer 10",
      "account_number": "XXXX4589",
      "ifsc_code": "HDFC0001234",
      "opening_balance": 85420,
      "closing_balance": 144291,
      "fraud_score": 8.0
    },
    {
      "document_id": "bank_statement_genuine_011",
      "document_type": "bank_statement",
      "label": "genuine",
      "ocr_confidence": 0.95,
      "account_holder": "Customer 11",
      "account_number": "XXXX4589",
      "ifsc_code": "HDFC0001234",
      "opening_balance": 85420,
      "closing_balance": 144291,
      "fraud_score": 8.0
    },
    {
      "document_id": "bank_statement_genuine_012",
      "document_type": "bank_statement",
      "label": "genuine",
      "ocr_confidence": 0.95,
      "account_holder": "Customer 12",
      "account_number": "XXXX4589",
      "ifsc_code": "HDFC0001234",
      "opening_balance": 85420,
      "closing_balance": 144291,
      "fraud_score": 8.0
    },
    {
      "document_id": "bank_statement_genuine_013",
      "document_type": "bank_statement",
      "label": "genuine",
      "ocr_confidence": 0.95,
      "account_holder": "Customer 13",
      "account_number": "XXXX4589",
      "ifsc_code": "HDFC0001234",
      "opening_balance": 85420,
      "closing_balance": 144291,
      "fraud_score": 8.0
    },
    {
      "document_id": "bank_statement_genuine_014",
      "document_type": "bank_statement",
      "label": "genuine",
      "ocr_confidence": 0.95,
      "account_holder": "Customer 14",
      "account_number": "XXXX4589",
      "ifsc_code": "HDFC0001234",
      "opening_balance": 85420,
      "closing_balance": 144291,
      "fraud_score": 8.0
    },
    {
      "document_id": "bank_statement_genuine_015",
      "document_type": "bank_statement",
      "label": "genuine",
      "ocr_confidence": 0.95,
      "account_holder": "Customer 15",
      "account_number": "XXXX4589",
      "ifsc_code": "HDFC0001234",
      "opening_balance": 85420,
      "closing_balance": 144291,
      "fraud_score": 8.0
    },
    {
      "document_id": "bank_statement_tampered_001",
      "document_type": "bank_statement",
      "label": "tampered",
      "ocr_confidence": 0.95,
      "account_holder": "Customer 1",
      "account_number": "XXXX4589",
      "ifsc_code": "HDFC0001234",
      "opening_balance": 85420,
      "closing_balance": 244291,
      "fraud_score": 98.0
    },
    {
      "document_id": "bank_statement_tampered_002",
      "document_type": "bank_statement",
      "label": "tampered",
      "ocr_confidence": 0.95,
      "account_holder": "Customer 2",
      "account_number": "XXXX4589",
      "ifsc_code": "HDFC0001234",
      "opening_balance": 85420,
      "closing_balance": 244291,
      "fraud_score": 98.0
    },
    {
      "document_id": "bank_statement_tampered_003",
      "document_type": "bank_statement",
      "label": "tampered",
      "ocr_confidence": 0.95,
      "account_holder": "Customer 3",
      "account_number": "XXXX4589",
      "ifsc_code": "HDFC0001234",
      "opening_balance": 85420,
      "closing_balance": 244291,
      "fraud_score": 98.0
    },
    {
      "document_id": "bank_statement_tampered_004",
      "document_type": "bank_statement",
      "label": "tampered",
      "ocr_confidence": 0.95,
      "account_holder": "Customer 4",
      "account_number": "XXXX4589",
      "ifsc_code": "HDFC0001234",
      "opening_balance": 85420,
      "closing_balance": 244291,
      "fraud_score": 98.0
    },
    {
      "document_id": "bank_statement_tampered_005",
      "document_type": "bank_statement",
      "label": "tampered",
      "ocr_confidence": 0.95,
      "account_holder": "Customer 5",
      "account_number": "XXXX4589",
      "ifsc_code": "HDFC0001234",
      "opening_balance": 85420,
      "closing_balance": 244291,
      "fraud_score": 98.0
    },
    {
      "document_id": "bank_statement_tampered_006",
      "document_type": "bank_statement",
      "label": "tampered",
      "ocr_confidence": 0.95,
      "account_holder": "Customer 6",
      "account_number": "XXXX4589",
      "ifsc_code": "HDFC0001234",
      "opening_balance": 85420,
      "closing_balance": 244291,
      "fraud_score": 98.0
    },
    {
      "document_id": "bank_statement_tampered_007",
      "document_type": "bank_statement",
      "label": "tampered",
      "ocr_confidence": 0.95,
      "account_holder": "Customer 7",
      "account_number": "XXXX4589",
      "ifsc_code": "HDFC0001234",
      "opening_balance": 85420,
      "closing_balance": 244291,
      "fraud_score": 98.0
    },
    {
      "document_id": "bank_statement_tampered_008",
      "document_type": "bank_statement",
      "label": "tampered",
      "ocr_confidence": 0.95,
      "account_holder": "Customer 8",
      "account_number": "XXXX4589",
      "ifsc_code": "HDFC0001234",
      "opening_balance": 85420,
      "closing_balance": 244291,
      "fraud_score": 98.0
    },
    {
      "document_id": "bank_statement_tampered_009",
      "document_type": "bank_statement",
      "label": "tampered",
      "ocr_confidence": 0.95,
      "account_holder": "Customer 9",
      "account_number": "XXXX4589",
      "ifsc_code": "HDFC0001234",
      "opening_balance": 85420,
      "closing_balance": 244291,
      "fraud_score": 98.0
    },
    {
      "document_id": "bank_statement_tampered_010",
      "document_type": "bank_statement",
      "label": "tampered",
      "ocr_confidence": 0.95,
      "account_holder": "Customer 10",
      "account_number": "XXXX4589",
      "ifsc_code": "HDFC0001234",
      "opening_balance": 85420,
      "closing_balance": 244291,
      "fraud_score": 98.0
    },
    {
      "document_id": "bank_statement_tampered_011",
      "document_type": "bank_statement",
      "label": "tampered",
      "ocr_confidence": 0.95,
      "account_holder": "Customer 11",
      "account_number": "XXXX4589",
      "ifsc_code": "HDFC0001234",
      "opening_balance": 85420,
      "closing_balance": 244291,
      "fraud_score": 98.0
    },
    {
      "document_id": "bank_statement_tampered_012",
      "document_type": "bank_statement",
      "label": "tampered",
      "ocr_confidence": 0.95,
      "account_holder": "Customer 12",
      "account_number": "XXXX4589",
      "ifsc_code": "HDFC0001234",
      "opening_balance": 85420,
      "closing_balance": 244291,
      "fraud_score": 98.0
    },
    {
      "document_id": "bank_statement_tampered_013",
      "document_type": "bank_statement",
      "label": "tampered",
      "ocr_confidence": 0.95,
      "account_holder": "Customer 13",
      "account_number": "XXXX4589",
      "ifsc_code": "HDFC0001234",
      "opening_balance": 85420,
      "closing_balance": 244291,
      "fraud_score": 98.0
    },
    {
      "document_id": "bank_statement_tampered_014",
      "document_type": "bank_statement",
      "label": "tampered",
      "ocr_confidence": 0.95,
      "account_holder": "Customer 14",
      "account_number": "XXXX4589",
      "ifsc_code": "HDFC0001234",
      "opening_balance": 85420,
      "closing_balance": 244291,
      "fraud_score": 98.0
    },
    {
      "document_id": "bank_statement_tampered_015",
      "document_type": "bank_statement",
      "label": "tampered",
      "ocr_confidence": 0.95,
      "account_holder": "Customer 15",
      "account_number": "XXXX4589",
      "ifsc_code": "HDFC0001234",
      "opening_balance": 85420,
      "closing_balance": 244291,
      "fraud_score": 98.0
    },
    {
      "document_id": "property_document_genuine_001",
      "document_type": "property_document",
      "label": "genuine",
      "ocr_confidence": 0.95,
      "owner_name": "Owner 1",
      "survey_number": "SN00001",
      "registration_number": "REG202600001",
      "market_value": 7500000,
      "fraud_score": 7.0
    },
    {
      "document_id": "property_document_genuine_002",
      "document_type": "property_document",
      "label": "genuine",
      "ocr_confidence": 0.95,
      "owner_name": "Owner 2",
      "survey_number": "SN00002",
      "registration_number": "REG202600002",
      "market_value": 7500000,
      "fraud_score": 7.0
    },
    {
      "document_id": "property_document_genuine_003",
      "document_type": "property_document",
      "label": "genuine",
      "ocr_confidence": 0.95,
      "owner_name": "Owner 3",
      "survey_number": "SN00003",
      "registration_number": "REG202600003",
      "market_value": 7500000,
      "fraud_score": 7.0
    },
    {
      "document_id": "property_document_genuine_004",
      "document_type": "property_document",
      "label": "genuine",
      "ocr_confidence": 0.95,
      "owner_name": "Owner 4",
      "survey_number": "SN00004",
      "registration_number": "REG202600004",
      "market_value": 7500000,
      "fraud_score": 7.0
    },
    {
      "document_id": "property_document_genuine_005",
      "document_type": "property_document",
      "label": "genuine",
      "ocr_confidence": 0.95,
      "owner_name": "Owner 5",
      "survey_number": "SN00005",
      "registration_number": "REG202600005",
      "market_value": 7500000,
      "fraud_score": 7.0
    },
    {
      "document_id": "property_document_genuine_006",
      "document_type": "property_document",
      "label": "genuine",
      "ocr_confidence": 0.95,
      "owner_name": "Owner 6",
      "survey_number": "SN00006",
      "registration_number": "REG202600006",
      "market_value": 7500000,
      "fraud_score": 7.0
    },
    {
      "document_id": "property_document_genuine_007",
      "document_type": "property_document",
      "label": "genuine",
      "ocr_confidence": 0.95,
      "owner_name": "Owner 7",
      "survey_number": "SN00007",
      "registration_number": "REG202600007",
      "market_value": 7500000,
      "fraud_score": 7.0
    },
    {
      "document_id": "property_document_genuine_008",
      "document_type": "property_document",
      "label": "genuine",
      "ocr_confidence": 0.95,
      "owner_name": "Owner 8",
      "survey_number": "SN00008",
      "registration_number": "REG202600008",
      "market_value": 7500000,
      "fraud_score": 7.0
    },
    {
      "document_id": "property_document_genuine_009",
      "document_type": "property_document",
      "label": "genuine",
      "ocr_confidence": 0.95,
      "owner_name": "Owner 9",
      "survey_number": "SN00009",
      "registration_number": "REG202600009",
      "market_value": 7500000,
      "fraud_score": 7.0
    },
    {
      "document_id": "property_document_genuine_010",
      "document_type": "property_document",
      "label": "genuine",
      "ocr_confidence": 0.95,
      "owner_name": "Owner 10",
      "survey_number": "SN00010",
      "registration_number": "REG202600010",
      "market_value": 7500000,
      "fraud_score": 7.0
    },
    {
      "document_id": "property_document_genuine_011",
      "document_type": "property_document",
      "label": "genuine",
      "ocr_confidence": 0.95,
      "owner_name": "Owner 11",
      "survey_number": "SN00011",
      "registration_number": "REG202600011",
      "market_value": 7500000,
      "fraud_score": 7.0
    },
    {
      "document_id": "property_document_genuine_012",
      "document_type": "property_document",
      "label": "genuine",
      "ocr_confidence": 0.95,
      "owner_name": "Owner 12",
      "survey_number": "SN00012",
      "registration_number": "REG202600012",
      "market_value": 7500000,
      "fraud_score": 7.0
    },
    {
      "document_id": "property_document_genuine_013",
      "document_type": "property_document",
      "label": "genuine",
      "ocr_confidence": 0.95,
      "owner_name": "Owner 13",
      "survey_number": "SN00013",
      "registration_number": "REG202600013",
      "market_value": 7500000,
      "fraud_score": 7.0
    },
    {
      "document_id": "property_document_genuine_014",
      "document_type": "property_document",
      "label": "genuine",
      "ocr_confidence": 0.95,
      "owner_name": "Owner 14",
      "survey_number": "SN00014",
      "registration_number": "REG202600014",
      "market_value": 7500000,
      "fraud_score": 7.0
    },
    {
      "document_id": "property_document_genuine_015",
      "document_type": "property_document",
      "label": "genuine",
      "ocr_confidence": 0.95,
      "owner_name": "Owner 15",
      "survey_number": "SN00015",
      "registration_number": "REG202600015",
      "market_value": 7500000,
      "fraud_score": 7.0
    },
    {
      "document_id": "property_document_tampered_001",
      "document_type": "property_document",
      "label": "tampered",
      "ocr_confidence": 0.95,
      "owner_name": "Fake Owner 1",
      "survey_number": "SN00001",
      "registration_number": "REG202600001",
      "market_value": 9500000,
      "fraud_score": 96.0
    },
    {
      "document_id": "property_document_tampered_002",
      "document_type": "property_document",
      "label": "tampered",
      "ocr_confidence": 0.95,
      "owner_name": "Fake Owner 2",
      "survey_number": "SN00002",
      "registration_number": "REG202600002",
      "market_value": 9500000,
      "fraud_score": 96.0
    },
    {
      "document_id": "property_document_tampered_003",
      "document_type": "property_document",
      "label": "tampered",
      "ocr_confidence": 0.95,
      "owner_name": "Fake Owner 3",
      "survey_number": "SN00003",
      "registration_number": "REG202600003",
      "market_value": 9500000,
      "fraud_score": 96.0
    },
    {
      "document_id": "property_document_tampered_004",
      "document_type": "property_document",
      "label": "tampered",
      "ocr_confidence": 0.95,
      "owner_name": "Fake Owner 4",
      "survey_number": "SN00004",
      "registration_number": "REG202600004",
      "market_value": 9500000,
      "fraud_score": 96.0
    },
    {
      "document_id": "property_document_tampered_005",
      "document_type": "property_document",
      "label": "tampered",
      "ocr_confidence": 0.95,
      "owner_name": "Fake Owner 5",
      "survey_number": "SN00005",
      "registration_number": "REG202600005",
      "market_value": 9500000,
      "fraud_score": 96.0
    },
    {
      "document_id": "property_document_tampered_006",
      "document_type": "property_document",
      "label": "tampered",
      "ocr_confidence": 0.95,
      "owner_name": "Fake Owner 6",
      "survey_number": "SN00006",
      "registration_number": "REG202600006",
      "market_value": 9500000,
      "fraud_score": 96.0
    },
    {
      "document_id": "property_document_tampered_007",
      "document_type": "property_document",
      "label": "tampered",
      "ocr_confidence": 0.95,
      "owner_name": "Fake Owner 7",
      "survey_number": "SN00007",
      "registration_number": "REG202600007",
      "market_value": 9500000,
      "fraud_score": 96.0
    },
    {
      "document_id": "property_document_tampered_008",
      "document_type": "property_document",
      "label": "tampered",
      "ocr_confidence": 0.95,
      "owner_name": "Fake Owner 8",
      "survey_number": "SN00008",
      "registration_number": "REG202600008",
      "market_value": 9500000,
      "fraud_score": 96.0
    },
    {
      "document_id": "property_document_tampered_009",
      "document_type": "property_document",
      "label": "tampered",
      "ocr_confidence": 0.95,
      "owner_name": "Fake Owner 9",
      "survey_number": "SN00009",
      "registration_number": "REG202600009",
      "market_value": 9500000,
      "fraud_score": 96.0
    },
    {
      "document_id": "property_document_tampered_010",
      "document_type": "property_document",
      "label": "tampered",
      "ocr_confidence": 0.95,
      "owner_name": "Fake Owner 10",
      "survey_number": "SN00010",
      "registration_number": "REG202600010",
      "market_value": 9500000,
      "fraud_score": 96.0
    },
    {
      "document_id": "property_document_tampered_011",
      "document_type": "property_document",
      "label": "tampered",
      "ocr_confidence": 0.95,
      "owner_name": "Fake Owner 11",
      "survey_number": "SN00011",
      "registration_number": "REG202600011",
      "market_value": 9500000,
      "fraud_score": 96.0
    },
    {
      "document_id": "property_document_tampered_012",
      "document_type": "property_document",
      "label": "tampered",
      "ocr_confidence": 0.95,
      "owner_name": "Fake Owner 12",
      "survey_number": "SN00012",
      "registration_number": "REG202600012",
      "market_value": 9500000,
      "fraud_score": 96.0
    },
    {
      "document_id": "property_document_tampered_013",
      "document_type": "property_document",
      "label": "tampered",
      "ocr_confidence": 0.95,
      "owner_name": "Fake Owner 13",
      "survey_number": "SN00013",
      "registration_number": "REG202600013",
      "market_value": 9500000,
      "fraud_score": 96.0
    },
    {
      "document_id": "property_document_tampered_014",
      "document_type": "property_document",
      "label": "tampered",
      "ocr_confidence": 0.95,
      "owner_name": "Fake Owner 14",
      "survey_number": "SN00014",
      "registration_number": "REG202600014",
      "market_value": 9500000,
      "fraud_score": 96.0
    },
    {
      "document_id": "property_document_tampered_015",
      "document_type": "property_document",
      "label": "tampered",
      "ocr_confidence": 0.95,
      "owner_name": "Fake Owner 15",
      "survey_number": "SN00015",
      "registration_number": "REG202600015",
      "market_value": 9500000,
      "fraud_score": 96.0
    }
  ]
}